[
  {
    "rows": 8,
    "cols": 8,
    "algo": "DFS",
    "mode": "Auto",
    "cost": 176,
    "time": 35,
    "steps": 4,
    "visited": 4629,
    "generated": 5330,
    "reshuffles": 4,
    "time_ms": 2.4,
    "total_visited": 4629,
    "total_generated": 5330,
    "state_key": "86919c2743980f1fef3d468f09e6d7d3",
    "state": 1
  },
  {
    "rows": 8,
    "cols": 8,
    "algo": "BFS",
    "mode": "Auto",
    "cost": 148,
    "time": 36,
    "steps": 4,
    "visited": 5751,
    "generated": 6595,
    "reshuffles": 1,
    "time_ms": 0.0,
    "total_visited": 5751,
    "total_generated": 6595,
    "state_key": "86919c2743980f1fef3d468f09e6d7d3",
    "state": 1
  },
  {
    "rows": 8,
    "cols": 8,
    "algo": "UCS",
    "mode": "Auto",
    "cost": 170,
    "time": 38,
    "steps": 2,
    "visited": 7003,
    "generated": 8008,
    "reshuffles": 1,
    "time_ms": 0.0,
    "total_visited": 7003,
    "total_generated": 8008,
    "state_key": "86919c2743980f1fef3d468f09e6d7d3",
    "state": 1
  },
  {
    "rows": 8,
    "cols": 8,
    "algo": "A*",
    "mode": "Auto",
    "cost": 170,
    "time": 26,
    "steps": 2,
    "visited": 7605,
    "generated": 8863,
    "reshuffles": 1,
    "time_ms": 0.0,
    "total_visited": 7605,
    "total_generated": 8863,
    "state_key": "86919c2743980f1fef3d468f09e6d7d3",
    "state": 1
  },
  {
    "rows": 8,
    "cols": 8,
    "algo": "HillClimb",
    "mode": "Auto",
    "cost": 140,
    "time": 21,
    "steps": 9,
    "visited": 7925,
    "generated": 9463,
    "reshuffles": 3,
    "time_ms": 0.0,
    "total_visited": 7925,
    "total_generated": 9463,
    "state_key": "86919c2743980f1fef3d468f09e6d7d3",
    "state": 1
  },
  {
    "rows": 8,
    "cols": 8,
    "algo": "DFS",
    "mode": "Auto",
    "cost": 148,
    "time": 35,
    "steps": 2,
    "visited": 8632,
    "generated": 10210,
    "reshuffles": 5,
    "time_ms": 2.0,
    "total_visited": 8632,
    "total_generated": 10210,
    "state_key": "5163998548ff1ad079bbef1e3f9e68ca",
    "state": 2
  },
  {
    "rows": 8,
    "cols": 8,
    "algo": "BFS",
    "mode": "Auto",
    "cost": 156,
    "time": 37,
    "steps": 7,
    "visited": 9806,
    "generated": 11561,
    "reshuffles": 3,
    "time_ms": 1.2,
    "total_visited": 9806,
    "total_generated": 11561,
    "state_key": "5163998548ff1ad079bbef1e3f9e68ca",
    "state": 2
  },
  {
    "rows": 8,
    "cols": 8,
    "algo": "UCS",
    "mode": "Auto",
    "cost": 160,
    "time": 35,
    "steps": 4,
    "visited": 10966,
    "generated": 12885,
    "reshuffles": 0,
    "time_ms": 1.0,
    "total_visited": 10966,
    "total_generated": 12885,
    "state_key": "5163998548ff1ad079bbef1e3f9e68ca",
    "state": 2
  },
  {
    "rows": 8,
    "cols": 8,
    "algo": "A*",
    "mode": "Auto",
    "cost": 160,
    "time": 25,
    "steps": 4,
    "visited": 11552,
    "generated": 13705,
    "reshuffles": 0,
    "time_ms": 1.0,
    "total_visited": 11552,
    "total_generated": 13705,
    "state_key": "5163998548ff1ad079bbef1e3f9e68ca",
    "state": 2
  },
  {
    "rows": 8,
    "cols": 8,
    "algo": "HillClimb",
    "mode": "Auto",
    "cost": 158,
    "time": 21,
    "steps": 4,
    "visited": 11930,
    "generated": 14503,
    "reshuffles": 2,
    "time_ms": 0.0,
    "total_visited": 11930,
    "total_generated": 14503,
    "state_key": "5163998548ff1ad079bbef1e3f9e68ca",
    "state": 2
  },
  {
    "rows": 10,
    "cols": 12,
    "algo": "DFS",
    "mode": "Auto",
    "cost": 524,
    "time": 100,
    "steps": 2,
    "visited": 2899,
    "generated": 2999,
    "reshuffles": 2,
    "time_ms": 3.0,
    "total_visited": 2899,
    "total_generated": 2999,
    "state_key": "4cbc5a59bf8fcf838ff32894cf9cddc0",
    "state": 3
  },
  {
    "rows": 10,
    "cols": 12,
    "algo": "BFS",
    "mode": "Auto",
    "cost": 358,
    "time": 87,
    "steps": 3,
    "visited": 6305,
    "generated": 6863,
    "reshuffles": 0,
    "time_ms": 0.0,
    "total_visited": 6305,
    "total_generated": 6863,
    "state_key": "4cbc5a59bf8fcf838ff32894cf9cddc0",
    "state": 3
  },
  {
    "rows": 10,
    "cols": 12,
    "algo": "UCS",
    "mode": "Auto",
    "cost": 378,
    "time": 100,
    "steps": 2,
    "visited": 10067,
    "generated": 11055,
    "reshuffles": 0,
    "time_ms": 0.0,
    "total_visited": 10067,
    "total_generated": 11055,
    "state_key": "4cbc5a59bf8fcf838ff32894cf9cddc0",
    "state": 3
  },
  {
    "rows": 10,
    "cols": 12,
    "algo": "A*",
    "mode": "Auto",
    "cost": 378,
    "time": 50,
    "steps": 2,
    "visited": 11421,
    "generated": 13019,
    "reshuffles": 0,
    "time_ms": 0.0,
    "total_visited": 11421,
    "total_generated": 13019,
    "state_key": "4cbc5a59bf8fcf838ff32894cf9cddc0",
    "state": 3
  },
  {
    "rows": 10,
    "cols": 12,
    "algo": "HillClimb",
    "mode": "Auto",
    "cost": 280,
    "time": 38,
    "steps": 3,
    "visited": 12063,
    "generated": 14390,
    "reshuffles": 2,
    "time_ms": 0.0,
    "total_visited": 12063,
    "total_generated": 14390,
    "state_key": "4cbc5a59bf8fcf838ff32894cf9cddc0",
    "state": 3
  },
  {
    "rows": 8,
    "cols": 8,
    "algo": "DFS",
    "mode": "Auto",
    "cost": 176,
    "time": 34,
    "steps": 5,
    "visited": 786,
    "generated": 822,
    "reshuffles": 2,
    "time_ms": 2.0,
    "total_visited": 786,
    "total_generated": 822,
    "state_key": "6721267a8f84b4f5ef23c30917c1fe49",
    "state": 4
  },
  {
    "rows": 8,
    "cols": 8,
    "algo": "Manual",
    "mode": "Manual",
    "cost": 152,
    "time": 116,
    "steps": 0,
    "visited": 0,
    "generated": 0,
    "reshuffles": 0,
    "time_ms": 0,
    "total_visited": 1256,
    "total_generated": 1363,
    "state_key": "0ecbf5a8432e98ff0970767165460bba",
    "state": 5
  },
  {
    "rows": 8,
    "cols": 8,
    "algo": "DFS",
    "mode": "Auto",
    "cost": 142,
    "time": 34,
    "steps": 4,
    "visited": 1160,
    "generated": 1238,
    "reshuffles": 2,
    "time_ms": 1.0,
    "total_visited": 1160,
    "total_generated": 1238,
    "state_key": "0acfdf536c32b05eecb16f7a76fc3b37",
    "state": 6
  }
]